temple/__init__.py
temple/check.py
temple/clean.py
temple/cli.py
temple/constants.py
temple/exceptions.py
temple/ls.py
temple/setup.py
temple/update.py
temple/utils.py
temple/version.py
temple/tests/__init__.py
temple/tests/conftest.py
temple/tests/test_check.py
temple/tests/test_clean.py
temple/tests/test_cli.py
temple/tests/test_ls.py
temple/tests/test_setup.py
temple/tests/test_update.py
temple/tests/test_utils.py
temple-1.4.8.dist-info/DESCRIPTION.rst
temple-1.4.8.dist-info/METADATA
temple-1.4.8.dist-info/RECORD
temple-1.4.8.dist-info/WHEEL
temple-1.4.8.dist-info/entry_points.txt
temple-1.4.8.dist-info/metadata.json
temple-1.4.8.dist-info/pbr.json
temple-1.4.8.dist-info/top_level.txt
