Metadata-Version: 2.0
Name: temple
Version: 1.4.8
Summary: Templated project management
Home-page: https://github.com/CloverHealth/temple
Author: Clover Health
Author-email: oss@cloverhealth.com
License: BSD 3-Clause
Platform: UNKNOWN
Classifier: Topic :: Internet :: WWW/HTTP :: Dynamic Content
Classifier: Intended Audience :: Developers
Classifier: Programming Language :: Python
Classifier: Programming Language :: Python :: 3
Classifier: Development Status :: 4 - Beta
Classifier: Operating System :: OS Independent
Requires-Dist: click (>=6.7)
Requires-Dist: cookiecutter (~=1.7.3)
Requires-Dist: pyyaml (>=3.12)
Requires-Dist: requests (>=2.13.0)
